pytorch_pyramid/__init__.py
pytorch_pyramid/pytorch_pyramid.py
pytorch_pyramid-1.0.0.dist-info/METADATA
pytorch_pyramid-1.0.0.dist-info/WHEEL
pytorch_pyramid-1.0.0.dist-info/RECORD
